{
  "type": "Program",
  "body": [
    {
      "type": "VariableDeclaration",
      "declarations": [
        {
          "type": "VariableDeclarator",
          "id": {
            "type": "Identifier",
            "name": "TITLEBAR_OPTS",
            "range": [
              6,
              19
            ],
            "loc": {
              "start": {
                "line": 1,
                "column": 6
              },
              "end": {
                "line": 1,
                "column": 19
              }
            }
          },
          "init": {
            "type": "ObjectExpression",
            "properties": [
              {
                "type": "Property",
                "key": {
                  "type": "Identifier",
                  "name": "register",
                  "range": [
                    25,
                    33
                  ],
                  "loc": {
                    "start": {
                      "line": 2,
                      "column": 1
                    },
                    "end": {
                      "line": 2,
                      "column": 9
                    }
                  }
                },
                "value": {
                  "type": "ObjectExpression",
                  "properties": [
                    {
                      "type": "Property",
                      "key": {
                        "type": "Identifier",
                        "name": "active",
                        "range": [
                          39,
                          45
                        ],
                        "loc": {
                          "start": {
                            "line": 3,
                            "column": 2
                          },
                          "end": {
                            "line": 3,
                            "column": 8
                          }
                        }
                      },
                      "value": {
                        "type": "Literal",
                        "value": true,
                        "raw": "true",
                        "range": [
                          47,
                          51
                        ],
                        "loc": {
                          "start": {
                            "line": 3,
                            "column": 10
                          },
                          "end": {
                            "line": 3,
                            "column": 14
                          }
                        }
                      },
                      "kind": "init",
                      "method": false,
                      "shorthand": false,
                      "computed": false,
                      "range": [
                        39,
                        51
                      ],
                      "loc": {
                        "start": {
                          "line": 3,
                          "column": 2
                        },
                        "end": {
                          "line": 3,
                          "column": 14
                        }
                      }
                    },
                    {
                      "type": "Property",
                      "key": {
                        "type": "Identifier",
                        "name": "label",
                        "range": [
                          55,
                          60
                        ],
                        "loc": {
                          "start": {
                            "line": 4,
                            "column": 2
                          },
                          "end": {
                            "line": 4,
                            "column": 7
                          }
                        }
                      },
                      "value": {
                        "type": "Literal",
                        "value": "Register now",
                        "raw": "'Register now'",
                        "range": [
                          62,
                          76
                        ],
                        "loc": {
                          "start": {
                            "line": 4,
                            "column": 9
                          },
                          "end": {
                            "line": 4,
                            "column": 23
                          }
                        }
                      },
                      "kind": "init",
                      "method": false,
                      "shorthand": false,
                      "computed": false,
                      "range": [
                        55,
                        76
                      ],
                      "loc": {
                        "start": {
                          "line": 4,
                          "column": 2
                        },
                        "end": {
                          "line": 4,
                          "column": 23
                        }
                      }
                    },
                    {
                      "type": "Property",
                      "key": {
                        "type": "Identifier",
                        "name": "tooltip",
                        "range": [
                          80,
                          87
                        ],
                        "loc": {
                          "start": {
                            "line": 5,
                            "column": 2
                          },
                          "end": {
                            "line": 5,
                            "column": 9
                          }
                        }
                      },
                      "value": {
                        "type": "Literal",
                        "value": false,
                        "raw": "false",
                        "range": [
                          89,
                          94
                        ],
                        "loc": {
                          "start": {
                            "line": 5,
                            "column": 11
                          },
                          "end": {
                            "line": 5,
                            "column": 16
                          }
                        }
                      },
                      "kind": "init",
                      "method": false,
                      "shorthand": false,
                      "computed": false,
                      "range": [
                        80,
                        94
                      ],
                      "loc": {
                        "start": {
                          "line": 5,
                          "column": 2
                        },
                        "end": {
                          "line": 5,
                          "column": 16
                        }
                      }
                    },
                    {
                      "type": "Property",
                      "key": {
                        "type": "Identifier",
                        "name": "icon",
                        "range": [
                          98,
                          102
                        ],
                        "loc": {
                          "start": {
                            "line": 6,
                            "column": 2
                          },
                          "end": {
                            "line": 6,
                            "column": 6
                          }
                        }
                      },
                      "value": {
                        "type": "ArrayExpression",
                        "elements": [
                          {
                            "type": "Literal",
                            "value": "person_outline",
                            "raw": "'person_outline'",
                            "range": [
                              105,
                              121
                            ],
                            "loc": {
                              "start": {
                                "line": 6,
                                "column": 9
                              },
                              "end": {
                                "line": 6,
                                "column": 25
                              }
                            }
                          },
                          {
                            "type": "Literal",
                            "value": "person_outline",
                            "raw": "'person_outline'",
                            "range": [
                              123,
                              139
                            ],
                            "loc": {
                              "start": {
                                "line": 6,
                                "column": 27
                              },
                              "end": {
                                "line": 6,
                                "column": 43
                              }
                            }
                          }
                        ],
                        "range": [
                          104,
                          140
                        ],
                        "loc": {
                          "start": {
                            "line": 6,
                            "column": 8
                          },
                          "end": {
                            "line": 6,
                            "column": 44
                          }
                        }
                      },
                      "kind": "init",
                      "method": false,
                      "shorthand": false,
                      "computed": false,
                      "range": [
                        98,
                        140
                      ],
                      "loc": {
                        "start": {
                          "line": 6,
                          "column": 2
                        },
                        "end": {
                          "line": 6,
                          "column": 44
                        }
                      }
                    },
                    {
                      "type": "Property",
                      "key": {
                        "type": "Identifier",
                        "name": "class",
                        "range": [
                          144,
                          149
                        ],
                        "loc": {
                          "start": {
                            "line": 7,
                            "column": 2
                          },
                          "end": {
                            "line": 7,
                            "column": 7
                          }
                        }
                      },
                      "value": {
                        "type": "Literal",
                        "value": "cta-button bg-pink",
                        "raw": "'cta-button bg-pink'",
                        "range": [
                          151,
                          171
                        ],
                        "loc": {
                          "start": {
                            "line": 7,
                            "column": 9
                          },
                          "end": {
                            "line": 7,
                            "column": 29
                          }
                        }
                      },
                      "kind": "init",
                      "method": false,
                      "shorthand": false,
                      "computed": false,
                      "range": [
                        144,
                        171
                      ],
                      "loc": {
                        "start": {
                          "line": 7,
                          "column": 2
                        },
                        "end": {
                          "line": 7,
                          "column": 29
                        }
                      }
                    }
                  ],
                  "range": [
                    35,
                    174
                  ],
                  "loc": {
                    "start": {
                      "line": 2,
                      "column": 11
                    },
                    "end": {
                      "line": 8,
                      "column": 2
                    }
                  }
                },
                "kind": "init",
                "method": false,
                "shorthand": false,
                "computed": false,
                "range": [
                  25,
                  174
                ],
                "loc": {
                  "start": {
                    "line": 2,
                    "column": 1
                  },
                  "end": {
                    "line": 8,
                    "column": 2
                  }
                }
              },
              {
                "type": "Property",
                "key": {
                  "type": "Identifier",
                  "name": "schedule",
                  "range": [
                    177,
                    185
                  ],
                  "loc": {
                    "start": {
                      "line": 9,
                      "column": 1
                    },
                    "end": {
                      "line": 9,
                      "column": 9
                    }
                  }
                },
                "value": {
                  "type": "ObjectExpression",
                  "properties": [
                    {
                      "type": "Property",
                      "key": {
                        "type": "Identifier",
                        "name": "active",
                        "range": [
                          191,
                          197
                        ],
                        "loc": {
                          "start": {
                            "line": 10,
                            "column": 2
                          },
                          "end": {
                            "line": 10,
                            "column": 8
                          }
                        }
                      },
                      "value": {
                        "type": "Literal",
                        "value": true,
                        "raw": "true",
                        "range": [
                          199,
                          203
                        ],
                        "loc": {
                          "start": {
                            "line": 10,
                            "column": 10
                          },
                          "end": {
                            "line": 10,
                            "column": 14
                          }
                        }
                      },
                      "kind": "init",
                      "method": false,
                      "shorthand": false,
                      "computed": false,
                      "range": [
                        191,
                        203
                      ],
                      "loc": {
                        "start": {
                          "line": 10,
                          "column": 2
                        },
                        "end": {
                          "line": 10,
                          "column": 14
                        }
                      }
                    },
                    {
                      "type": "Property",
                      "key": {
                        "type": "Identifier",
                        "name": "label",
                        "range": [
                          207,
                          212
                        ],
                        "loc": {
                          "start": {
                            "line": 11,
                            "column": 2
                          },
                          "end": {
                            "line": 11,
                            "column": 7
                          }
                        }
                      },
                      "value": {
                        "type": "Literal",
                        "value": "Schedule visit",
                        "raw": "'Schedule visit'",
                        "range": [
                          214,
                          230
                        ],
                        "loc": {
                          "start": {
                            "line": 11,
                            "column": 9
                          },
                          "end": {
                            "line": 11,
                            "column": 25
                          }
                        }
                      },
                      "kind": "init",
                      "method": false,
                      "shorthand": false,
                      "computed": false,
                      "range": [
                        207,
                        230
                      ],
                      "loc": {
                        "start": {
                          "line": 11,
                          "column": 2
                        },
                        "end": {
                          "line": 11,
                          "column": 25
                        }
                      }
                    },
                    {
                      "type": "Property",
                      "key": {
                        "type": "Identifier",
                        "name": "tooltip",
                        "range": [
                          234,
                          241
                        ],
                        "loc": {
                          "start": {
                            "line": 12,
                            "column": 2
                          },
                          "end": {
                            "line": 12,
                            "column": 9
                          }
                        }
                      },
                      "value": {
                        "type": "Literal",
                        "value": false,
                        "raw": "false",
                        "range": [
                          243,
                          248
                        ],
                        "loc": {
                          "start": {
                            "line": 12,
                            "column": 11
                          },
                          "end": {
                            "line": 12,
                            "column": 16
                          }
                        }
                      },
                      "kind": "init",
                      "method": false,
                      "shorthand": false,
                      "computed": false,
                      "range": [
                        234,
                        248
                      ],
                      "loc": {
                        "start": {
                          "line": 12,
                          "column": 2
                        },
                        "end": {
                          "line": 12,
                          "column": 16
                        }
                      }
                    },
                    {
                      "type": "Property",
                      "key": {
                        "type": "Identifier",
                        "name": "icon",
                        "range": [
                          252,
                          256
                        ],
                        "loc": {
                          "start": {
                            "line": 13,
                            "column": 2
                          },
                          "end": {
                            "line": 13,
                            "column": 6
                          }
                        }
                      },
                      "value": {
                        "type": "ArrayExpression",
                        "elements": [
                          {
                            "type": "Literal",
                            "value": "add_alarm",
                            "raw": "'add_alarm'",
                            "range": [
                              259,
                              270
                            ],
                            "loc": {
                              "start": {
                                "line": 13,
                                "column": 9
                              },
                              "end": {
                                "line": 13,
                                "column": 20
                              }
                            }
                          },
                          {
                            "type": "Literal",
                            "value": "add_alarm",
                            "raw": "'add_alarm'",
                            "range": [
                              272,
                              283
                            ],
                            "loc": {
                              "start": {
                                "line": 13,
                                "column": 22
                              },
                              "end": {
                                "line": 13,
                                "column": 33
                              }
                            }
                          }
                        ],
                        "range": [
                          258,
                          284
                        ],
                        "loc": {
                          "start": {
                            "line": 13,
                            "column": 8
                          },
                          "end": {
                            "line": 13,
                            "column": 34
                          }
                        }
                      },
                      "kind": "init",
                      "method": false,
                      "shorthand": false,
                      "computed": false,
                      "range": [
                        252,
                        284
                      ],
                      "loc": {
                        "start": {
                          "line": 13,
                          "column": 2
                        },
                        "end": {
                          "line": 13,
                          "column": 34
                        }
                      }
                    },
                    {
                      "type": "Property",
                      "key": {
                        "type": "Identifier",
                        "name": "class",
                        "range": [
                          288,
                          293
                        ],
                        "loc": {
                          "start": {
                            "line": 14,
                            "column": 2
                          },
                          "end": {
                            "line": 14,
                            "column": 7
                          }
                        }
                      },
                      "value": {
                        "type": "Literal",
                        "value": "cta-button bg-green",
                        "raw": "'cta-button bg-green'",
                        "range": [
                          295,
                          316
                        ],
                        "loc": {
                          "start": {
                            "line": 14,
                            "column": 9
                          },
                          "end": {
                            "line": 14,
                            "column": 30
                          }
                        }
                      },
                      "kind": "init",
                      "method": false,
                      "shorthand": false,
                      "computed": false,
                      "range": [
                        288,
                        316
                      ],
                      "loc": {
                        "start": {
                          "line": 14,
                          "column": 2
                        },
                        "end": {
                          "line": 14,
                          "column": 30
                        }
                      }
                    }
                  ],
                  "range": [
                    187,
                    319
                  ],
                  "loc": {
                    "start": {
                      "line": 9,
                      "column": 11
                    },
                    "end": {
                      "line": 15,
                      "column": 2
                    }
                  }
                },
                "kind": "init",
                "method": false,
                "shorthand": false,
                "computed": false,
                "range": [
                  177,
                  319
                ],
                "loc": {
                  "start": {
                    "line": 9,
                    "column": 1
                  },
                  "end": {
                    "line": 15,
                    "column": 2
                  }
                }
              },
              {
                "type": "Property",
                "key": {
                  "type": "Identifier",
                  "name": "apply",
                  "range": [
                    322,
                    327
                  ],
                  "loc": {
                    "start": {
                      "line": 16,
                      "column": 1
                    },
                    "end": {
                      "line": 16,
                      "column": 6
                    }
                  }
                },
                "value": {
                  "type": "ObjectExpression",
                  "properties": [
                    {
                      "type": "Property",
                      "key": {
                        "type": "Identifier",
                        "name": "active",
                        "range": [
                          333,
                          339
                        ],
                        "loc": {
                          "start": {
                            "line": 17,
                            "column": 2
                          },
                          "end": {
                            "line": 17,
                            "column": 8
                          }
                        }
                      },
                      "value": {
                        "type": "Literal",
                        "value": true,
                        "raw": "true",
                        "range": [
                          341,
                          345
                        ],
                        "loc": {
                          "start": {
                            "line": 17,
                            "column": 10
                          },
                          "end": {
                            "line": 17,
                            "column": 14
                          }
                        }
                      },
                      "kind": "init",
                      "method": false,
                      "shorthand": false,
                      "computed": false,
                      "range": [
                        333,
                        345
                      ],
                      "loc": {
                        "start": {
                          "line": 17,
                          "column": 2
                        },
                        "end": {
                          "line": 17,
                          "column": 14
                        }
                      }
                    },
                    {
                      "type": "Property",
                      "key": {
                        "type": "Identifier",
                        "name": "label",
                        "range": [
                          349,
                          354
                        ],
                        "loc": {
                          "start": {
                            "line": 18,
                            "column": 2
                          },
                          "end": {
                            "line": 18,
                            "column": 7
                          }
                        }
                      },
                      "value": {
                        "type": "Literal",
                        "value": "Apply online",
                        "raw": "'Apply online'",
                        "range": [
                          356,
                          370
                        ],
                        "loc": {
                          "start": {
                            "line": 18,
                            "column": 9
                          },
                          "end": {
                            "line": 18,
                            "column": 23
                          }
                        }
                      },
                      "kind": "init",
                      "method": false,
                      "shorthand": false,
                      "computed": false,
                      "range": [
                        349,
                        370
                      ],
                      "loc": {
                        "start": {
                          "line": 18,
                          "column": 2
                        },
                        "end": {
                          "line": 18,
                          "column": 23
                        }
                      }
                    },
                    {
                      "type": "Property",
                      "key": {
                        "type": "Identifier",
                        "name": "tooltip",
                        "range": [
                          374,
                          381
                        ],
                        "loc": {
                          "start": {
                            "line": 19,
                            "column": 2
                          },
                          "end": {
                            "line": 19,
                            "column": 9
                          }
                        }
                      },
                      "value": {
                        "type": "Literal",
                        "value": false,
                        "raw": "false",
                        "range": [
                          383,
                          388
                        ],
                        "loc": {
                          "start": {
                            "line": 19,
                            "column": 11
                          },
                          "end": {
                            "line": 19,
                            "column": 16
                          }
                        }
                      },
                      "kind": "init",
                      "method": false,
                      "shorthand": false,
                      "computed": false,
                      "range": [
                        374,
                        388
                      ],
                      "loc": {
                        "start": {
                          "line": 19,
                          "column": 2
                        },
                        "end": {
                          "line": 19,
                          "column": 16
                        }
                      }
                    },
                    {
                      "type": "Property",
                      "key": {
                        "type": "Identifier",
                        "name": "icon",
                        "range": [
                          392,
                          396
                        ],
                        "loc": {
                          "start": {
                            "line": 20,
                            "column": 2
                          },
                          "end": {
                            "line": 20,
                            "column": 6
                          }
                        }
                      },
                      "value": {
                        "type": "ArrayExpression",
                        "elements": [
                          {
                            "type": "Literal",
                            "value": "bookmark_outline",
                            "raw": "'bookmark_outline'",
                            "range": [
                              399,
                              417
                            ],
                            "loc": {
                              "start": {
                                "line": 20,
                                "column": 9
                              },
                              "end": {
                                "line": 20,
                                "column": 27
                              }
                            }
                          },
                          {
                            "type": "Literal",
                            "value": "bookmark_outline",
                            "raw": "'bookmark_outline'",
                            "range": [
                              419,
                              437
                            ],
                            "loc": {
                              "start": {
                                "line": 20,
                                "column": 29
                              },
                              "end": {
                                "line": 20,
                                "column": 47
                              }
                            }
                          }
                        ],
                        "range": [
                          398,
                          438
                        ],
                        "loc": {
                          "start": {
                            "line": 20,
                            "column": 8
                          },
                          "end": {
                            "line": 20,
                            "column": 48
                          }
                        }
                      },
                      "kind": "init",
                      "method": false,
                      "shorthand": false,
                      "computed": false,
                      "range": [
                        392,
                        438
                      ],
                      "loc": {
                        "start": {
                          "line": 20,
                          "column": 2
                        },
                        "end": {
                          "line": 20,
                          "column": 48
                        }
                      }
                    },
                    {
                      "type": "Property",
                      "key": {
                        "type": "Identifier",
                        "name": "class",
                        "range": [
                          442,
                          447
                        ],
                        "loc": {
                          "start": {
                            "line": 21,
                            "column": 2
                          },
                          "end": {
                            "line": 21,
                            "column": 7
                          }
                        }
                      },
                      "value": {
                        "type": "Literal",
                        "value": "cta-button bg-orange",
                        "raw": "'cta-button bg-orange'",
                        "range": [
                          449,
                          471
                        ],
                        "loc": {
                          "start": {
                            "line": 21,
                            "column": 9
                          },
                          "end": {
                            "line": 21,
                            "column": 31
                          }
                        }
                      },
                      "kind": "init",
                      "method": false,
                      "shorthand": false,
                      "computed": false,
                      "range": [
                        442,
                        471
                      ],
                      "loc": {
                        "start": {
                          "line": 21,
                          "column": 2
                        },
                        "end": {
                          "line": 21,
                          "column": 31
                        }
                      }
                    }
                  ],
                  "range": [
                    329,
                    474
                  ],
                  "loc": {
                    "start": {
                      "line": 16,
                      "column": 8
                    },
                    "end": {
                      "line": 22,
                      "column": 2
                    }
                  }
                },
                "kind": "init",
                "method": false,
                "shorthand": false,
                "computed": false,
                "range": [
                  322,
                  474
                ],
                "loc": {
                  "start": {
                    "line": 16,
                    "column": 1
                  },
                  "end": {
                    "line": 22,
                    "column": 2
                  }
                }
              },
              {
                "type": "Property",
                "key": {
                  "type": "Identifier",
                  "name": "condense",
                  "range": [
                    477,
                    485
                  ],
                  "loc": {
                    "start": {
                      "line": 23,
                      "column": 1
                    },
                    "end": {
                      "line": 23,
                      "column": 9
                    }
                  }
                },
                "value": {
                  "type": "ObjectExpression",
                  "properties": [
                    {
                      "type": "Property",
                      "key": {
                        "type": "Identifier",
                        "name": "active",
                        "range": [
                          491,
                          497
                        ],
                        "loc": {
                          "start": {
                            "line": 24,
                            "column": 2
                          },
                          "end": {
                            "line": 24,
                            "column": 8
                          }
                        }
                      },
                      "value": {
                        "type": "Literal",
                        "value": true,
                        "raw": "true",
                        "range": [
                          499,
                          503
                        ],
                        "loc": {
                          "start": {
                            "line": 24,
                            "column": 10
                          },
                          "end": {
                            "line": 24,
                            "column": 14
                          }
                        }
                      },
                      "kind": "init",
                      "method": false,
                      "shorthand": false,
                      "computed": false,
                      "range": [
                        491,
                        503
                      ],
                      "loc": {
                        "start": {
                          "line": 24,
                          "column": 2
                        },
                        "end": {
                          "line": 24,
                          "column": 14
                        }
                      }
                    },
                    {
                      "type": "Property",
                      "key": {
                        "type": "Identifier",
                        "name": "label",
                        "range": [
                          507,
                          512
                        ],
                        "loc": {
                          "start": {
                            "line": 25,
                            "column": 2
                          },
                          "end": {
                            "line": 25,
                            "column": 7
                          }
                        }
                      },
                      "value": {
                        "type": "Literal",
                        "value": "Toolbar size",
                        "raw": "'Toolbar size'",
                        "range": [
                          514,
                          528
                        ],
                        "loc": {
                          "start": {
                            "line": 25,
                            "column": 9
                          },
                          "end": {
                            "line": 25,
                            "column": 23
                          }
                        }
                      },
                      "kind": "init",
                      "method": false,
                      "shorthand": false,
                      "computed": false,
                      "range": [
                        507,
                        528
                      ],
                      "loc": {
                        "start": {
                          "line": 25,
                          "column": 2
                        },
                        "end": {
                          "line": 25,
                          "column": 23
                        }
                      }
                    },
                    {
                      "type": "Property",
                      "key": {
                        "type": "Identifier",
                        "name": "tooltip",
                        "range": [
                          532,
                          539
                        ],
                        "loc": {
                          "start": {
                            "line": 26,
                            "column": 2
                          },
                          "end": {
                            "line": 26,
                            "column": 9
                          }
                        }
                      },
                      "value": {
                        "type": "ArrayExpression",
                        "elements": [
                          {
                            "type": "Literal",
                            "value": "Expand toolbar",
                            "raw": "'Expand toolbar'",
                            "range": [
                              543,
                              559
                            ],
                            "loc": {
                              "start": {
                                "line": 26,
                                "column": 13
                              },
                              "end": {
                                "line": 26,
                                "column": 29
                              }
                            }
                          },
                          {
                            "type": "Literal",
                            "value": "Condense toolbar",
                            "raw": "'Condense toolbar'",
                            "range": [
                              561,
                              579
                            ],
                            "loc": {
                              "start": {
                                "line": 26,
                                "column": 31
                              },
                              "end": {
                                "line": 26,
                                "column": 49
                              }
                            }
                          }
                        ],
                        "range": [
                          541,
                          581
                        ],
                        "loc": {
                          "start": {
                            "line": 26,
                            "column": 11
                          },
                          "end": {
                            "line": 26,
                            "column": 51
                          }
                        }
                      },
                      "kind": "init",
                      "method": false,
                      "shorthand": false,
                      "computed": false,
                      "range": [
                        532,
                        581
                      ],
                      "loc": {
                        "start": {
                          "line": 26,
                          "column": 2
                        },
                        "end": {
                          "line": 26,
                          "column": 51
                        }
                      }
                    },
                    {
                      "type": "Property",
                      "key": {
                        "type": "Identifier",
                        "name": "icon",
                        "range": [
                          585,
                          589
                        ],
                        "loc": {
                          "start": {
                            "line": 27,
                            "column": 2
                          },
                          "end": {
                            "line": 27,
                            "column": 6
                          }
                        }
                      },
                      "value": {
                        "type": "ArrayExpression",
                        "elements": [
                          {
                            "type": "Literal",
                            "value": "flip_to_front",
                            "raw": "'flip_to_front'",
                            "range": [
                              593,
                              608
                            ],
                            "loc": {
                              "start": {
                                "line": 27,
                                "column": 10
                              },
                              "end": {
                                "line": 27,
                                "column": 25
                              }
                            }
                          },
                          {
                            "type": "Literal",
                            "value": "flip_to_back",
                            "raw": "'flip_to_back'",
                            "range": [
                              610,
                              624
                            ],
                            "loc": {
                              "start": {
                                "line": 27,
                                "column": 27
                              },
                              "end": {
                                "line": 27,
                                "column": 41
                              }
                            }
                          }
                        ],
                        "range": [
                          591,
                          626
                        ],
                        "loc": {
                          "start": {
                            "line": 27,
                            "column": 8
                          },
                          "end": {
                            "line": 27,
                            "column": 43
                          }
                        }
                      },
                      "kind": "init",
                      "method": false,
                      "shorthand": false,
                      "computed": false,
                      "range": [
                        585,
                        626
                      ],
                      "loc": {
                        "start": {
                          "line": 27,
                          "column": 2
                        },
                        "end": {
                          "line": 27,
                          "column": 43
                        }
                      }
                    }
                  ],
                  "range": [
                    487,
                    629
                  ],
                  "loc": {
                    "start": {
                      "line": 23,
                      "column": 11
                    },
                    "end": {
                      "line": 28,
                      "column": 2
                    }
                  }
                },
                "kind": "init",
                "method": false,
                "shorthand": false,
                "computed": false,
                "range": [
                  477,
                  629
                ],
                "loc": {
                  "start": {
                    "line": 23,
                    "column": 1
                  },
                  "end": {
                    "line": 28,
                    "column": 2
                  }
                }
              },
              {
                "type": "Property",
                "key": {
                  "type": "Identifier",
                  "name": "right",
                  "range": [
                    632,
                    637
                  ],
                  "loc": {
                    "start": {
                      "line": 29,
                      "column": 1
                    },
                    "end": {
                      "line": 29,
                      "column": 6
                    }
                  }
                },
                "value": {
                  "type": "ObjectExpression",
                  "properties": [
                    {
                      "type": "Property",
                      "key": {
                        "type": "Identifier",
                        "name": "active",
                        "range": [
                          643,
                          649
                        ],
                        "loc": {
                          "start": {
                            "line": 30,
                            "column": 2
                          },
                          "end": {
                            "line": 30,
                            "column": 8
                          }
                        }
                      },
                      "value": {
                        "type": "Literal",
                        "value": true,
                        "raw": "true",
                        "range": [
                          651,
                          655
                        ],
                        "loc": {
                          "start": {
                            "line": 30,
                            "column": 10
                          },
                          "end": {
                            "line": 30,
                            "column": 14
                          }
                        }
                      },
                      "kind": "init",
                      "method": false,
                      "shorthand": false,
                      "computed": false,
                      "range": [
                        643,
                        655
                      ],
                      "loc": {
                        "start": {
                          "line": 30,
                          "column": 2
                        },
                        "end": {
                          "line": 30,
                          "column": 14
                        }
                      }
                    },
                    {
                      "type": "Property",
                      "key": {
                        "type": "Identifier",
                        "name": "label",
                        "range": [
                          659,
                          664
                        ],
                        "loc": {
                          "start": {
                            "line": 31,
                            "column": 2
                          },
                          "end": {
                            "line": 31,
                            "column": 7
                          }
                        }
                      },
                      "value": {
                        "type": "Literal",
                        "value": "Toolbar visibility",
                        "raw": "'Toolbar visibility'",
                        "range": [
                          666,
                          686
                        ],
                        "loc": {
                          "start": {
                            "line": 31,
                            "column": 9
                          },
                          "end": {
                            "line": 31,
                            "column": 29
                          }
                        }
                      },
                      "kind": "init",
                      "method": false,
                      "shorthand": false,
                      "computed": false,
                      "range": [
                        659,
                        686
                      ],
                      "loc": {
                        "start": {
                          "line": 31,
                          "column": 2
                        },
                        "end": {
                          "line": 31,
                          "column": 29
                        }
                      }
                    },
                    {
                      "type": "Property",
                      "key": {
                        "type": "Identifier",
                        "name": "tooltip",
                        "range": [
                          690,
                          697
                        ],
                        "loc": {
                          "start": {
                            "line": 32,
                            "column": 2
                          },
                          "end": {
                            "line": 32,
                            "column": 9
                          }
                        }
                      },
                      "value": {
                        "type": "ArrayExpression",
                        "elements": [
                          {
                            "type": "Literal",
                            "value": "Hide toolbar",
                            "raw": "'Hide toolbar'",
                            "range": [
                              701,
                              715
                            ],
                            "loc": {
                              "start": {
                                "line": 32,
                                "column": 13
                              },
                              "end": {
                                "line": 32,
                                "column": 27
                              }
                            }
                          },
                          {
                            "type": "Literal",
                            "value": "Show toolbar",
                            "raw": "'Show toolbar'",
                            "range": [
                              717,
                              731
                            ],
                            "loc": {
                              "start": {
                                "line": 32,
                                "column": 29
                              },
                              "end": {
                                "line": 32,
                                "column": 43
                              }
                            }
                          }
                        ],
                        "range": [
                          699,
                          733
                        ],
                        "loc": {
                          "start": {
                            "line": 32,
                            "column": 11
                          },
                          "end": {
                            "line": 32,
                            "column": 45
                          }
                        }
                      },
                      "kind": "init",
                      "method": false,
                      "shorthand": false,
                      "computed": false,
                      "range": [
                        690,
                        733
                      ],
                      "loc": {
                        "start": {
                          "line": 32,
                          "column": 2
                        },
                        "end": {
                          "line": 32,
                          "column": 45
                        }
                      }
                    },
                    {
                      "type": "Property",
                      "key": {
                        "type": "Identifier",
                        "name": "icon",
                        "range": [
                          737,
                          741
                        ],
                        "loc": {
                          "start": {
                            "line": 33,
                            "column": 2
                          },
                          "end": {
                            "line": 33,
                            "column": 6
                          }
                        }
                      },
                      "value": {
                        "type": "ArrayExpression",
                        "elements": [
                          {
                            "type": "Literal",
                            "value": "last_page",
                            "raw": "'last_page'",
                            "range": [
                              745,
                              756
                            ],
                            "loc": {
                              "start": {
                                "line": 33,
                                "column": 10
                              },
                              "end": {
                                "line": 33,
                                "column": 21
                              }
                            }
                          },
                          {
                            "type": "Literal",
                            "value": "first_page",
                            "raw": "'first_page'",
                            "range": [
                              758,
                              770
                            ],
                            "loc": {
                              "start": {
                                "line": 33,
                                "column": 23
                              },
                              "end": {
                                "line": 33,
                                "column": 35
                              }
                            }
                          }
                        ],
                        "range": [
                          743,
                          772
                        ],
                        "loc": {
                          "start": {
                            "line": 33,
                            "column": 8
                          },
                          "end": {
                            "line": 33,
                            "column": 37
                          }
                        }
                      },
                      "kind": "init",
                      "method": false,
                      "shorthand": false,
                      "computed": false,
                      "range": [
                        737,
                        772
                      ],
                      "loc": {
                        "start": {
                          "line": 33,
                          "column": 2
                        },
                        "end": {
                          "line": 33,
                          "column": 37
                        }
                      }
                    }
                  ],
                  "range": [
                    639,
                    775
                  ],
                  "loc": {
                    "start": {
                      "line": 29,
                      "column": 8
                    },
                    "end": {
                      "line": 34,
                      "column": 2
                    }
                  }
                },
                "kind": "init",
                "method": false,
                "shorthand": false,
                "computed": false,
                "range": [
                  632,
                  775
                ],
                "loc": {
                  "start": {
                    "line": 29,
                    "column": 1
                  },
                  "end": {
                    "line": 34,
                    "column": 2
                  }
                }
              }
            ],
            "range": [
              22,
              777
            ],
            "loc": {
              "start": {
                "line": 1,
                "column": 22
              },
              "end": {
                "line": 35,
                "column": 1
              }
            }
          },
          "range": [
            6,
            777
          ],
          "loc": {
            "start": {
              "line": 1,
              "column": 6
            },
            "end": {
              "line": 35,
              "column": 1
            }
          }
        }
      ],
      "kind": "const",
      "range": [
        0,
        778
      ],
      "loc": {
        "start": {
          "line": 1,
          "column": 0
        },
        "end": {
          "line": 35,
          "column": 2
        }
      }
    },
    {
      "type": "ExportDefaultDeclaration",
      "declaration": {
        "type": "ObjectExpression",
        "properties": [
          {
            "type": "Property",
            "key": {
              "type": "Identifier",
              "name": "name",
              "range": [
                799,
                803
              ],
              "loc": {
                "start": {
                  "line": 38,
                  "column": 2
                },
                "end": {
                  "line": 38,
                  "column": 6
                }
              }
            },
            "value": {
              "type": "Literal",
              "value": "TITLEBAR_OPTS",
              "raw": "'TITLEBAR_OPTS'",
              "range": [
                805,
                820
              ],
              "loc": {
                "start": {
                  "line": 38,
                  "column": 8
                },
                "end": {
                  "line": 38,
                  "column": 23
                }
              }
            },
            "kind": "init",
            "method": false,
            "shorthand": false,
            "computed": false,
            "range": [
              799,
              820
            ],
            "loc": {
              "start": {
                "line": 38,
                "column": 2
              },
              "end": {
                "line": 38,
                "column": 23
              }
            }
          },
          {
            "type": "Property",
            "key": {
              "type": "Identifier",
              "name": "fn",
              "range": [
                824,
                826
              ],
              "loc": {
                "start": {
                  "line": 39,
                  "column": 2
                },
                "end": {
                  "line": 39,
                  "column": 4
                }
              }
            },
            "value": {
              "type": "Identifier",
              "name": "TITLEBAR_OPTS",
              "range": [
                828,
                841
              ],
              "loc": {
                "start": {
                  "line": 39,
                  "column": 6
                },
                "end": {
                  "line": 39,
                  "column": 19
                }
              }
            },
            "kind": "init",
            "method": false,
            "shorthand": false,
            "computed": false,
            "range": [
              824,
              841
            ],
            "loc": {
              "start": {
                "line": 39,
                "column": 2
              },
              "end": {
                "line": 39,
                "column": 19
              }
            }
          }
        ],
        "range": [
          795,
          843
        ],
        "loc": {
          "start": {
            "line": 37,
            "column": 15
          },
          "end": {
            "line": 40,
            "column": 1
          }
        },
        "leadingComments": [],
        "trailingComments": []
      },
      "range": [
        780,
        844
      ],
      "loc": {
        "start": {
          "line": 37,
          "column": 0
        },
        "end": {
          "line": 40,
          "column": 2
        }
      }
    }
  ],
  "sourceType": "module",
  "range": [
    0,
    844
  ],
  "loc": {
    "start": {
      "line": 1,
      "column": 0
    },
    "end": {
      "line": 40,
      "column": 2
    }
  },
  "comments": []
}